gtar/__init__.py
gtar/_gtar.cpython-36m-x86_64-linux-gnu.so
gtar/cat.py
gtar/copy.py
gtar/fix.py
gtar/read.py
gtar/version.py
gtar-1.1.3.dist-info/LICENSE
gtar-1.1.3.dist-info/METADATA
gtar-1.1.3.dist-info/WHEEL
gtar-1.1.3.dist-info/top_level.txt
gtar-1.1.3.dist-info/RECORD
